app_loader
